firipy/__init__.py
firipy/api.py
firipy-0.1.0.dist-info/METADATA
firipy-0.1.0.dist-info/WHEEL
firipy-0.1.0.dist-info/licenses/LICENSE
firipy-0.1.0.dist-info/RECORD
