Metadata-Version: 2.4
Name: firipy
Version: 0.1.0
Summary: Firipy is a Python wrapper for the Firi API. It provides a simple and intuitive way to interact with the Firi cryptocurrency exchange, allowing users to retrieve market data, manage orders, and more. With Firipy, you can easily integrate Firi's features into your Python applications.
Project-URL: Homepage, https://github.com/jeircul/firipy
Project-URL: Bug Tracker, https://github.com/jeircul/firipy/issues
Author-email: Ove Aursland <jeircul@outlook.com>
License: MIT
License-File: LICENSE
Keywords: api,crypto,exchange,firi,trading
Classifier: License :: OSI Approved :: MIT License
Classifier: Operating System :: OS Independent
Classifier: Programming Language :: Python :: 3
Requires-Python: >=3.9
Requires-Dist: requests<3,>=2.31
Provides-Extra: dev
Requires-Dist: build>=1.2.0; extra == 'dev'
Requires-Dist: mypy>=1.8; extra == 'dev'
Requires-Dist: pytest-cov>=4; extra == 'dev'
Requires-Dist: pytest>=7; extra == 'dev'
Requires-Dist: ruff>=0.2.0; extra == 'dev'
Requires-Dist: twine>=5.0.0; extra == 'dev'
Requires-Dist: types-requests; extra == 'dev'
